[
  {
    "invitation": [
      {
        "id": "7dfd62f9-ff1b-4df0-a25c-64e8b4161348",
        "status": "Sent",
        "expiry_date": "2023-09-04T11:28:45.847Z",
        "created_at": "2023-09-04T07:02:40.323Z",
        "updated_at": "2023-09-04T21:16:52.732Z",
        "company_id": "main_entity_pk",
        "user_id": "user_entity_pk"
      },
      {
        "id": "52ad83d2-abf2-4b5d-bc65-1698fbc36504",
        "status": "Accepted",
        "expiry_date": "2023-09-05T00:19:41.843Z",
        "created_at": "2023-09-04T09:31:12.937Z",
        "updated_at": "2023-09-05T04:26:07.817Z",
        "company_id": "main_entity_pk",
        "user_id": "user_entity_pk"
      },
      {
        "id": "a82aa132-e703-481f-9809-194828bf0b07",
        "status": "Declined",
        "expiry_date": "2023-09-04T21:17:13.707Z",
        "created_at": "2023-09-05T01:58:09.488Z",
        "updated_at": "2023-09-04T21:40:13.488Z",
        "company_id": "main_entity_pk",
        "user_id": "user_entity_pk"
      },
      {
        "id": "727b41e8-3f58-42dc-a816-7479b926aa34",
        "status": "Pending",
        "expiry_date": "2023-09-04T18:20:25.809Z",
        "created_at": "2023-09-04T12:45:03.550Z",
        "updated_at": "2023-09-04T19:09:58.251Z",
        "company_id": "main_entity_pk",
        "user_id": "user_entity_pk"
      },
      {
        "id": "60deb6ac-c385-445a-acea-69d28346b756",
        "status": "Expired",
        "expiry_date": "2023-09-05T00:09:35.537Z",
        "created_at": "2023-09-04T22:12:58.269Z",
        "updated_at": "2023-09-04T13:19:06.779Z",
        "company_id": "main_entity_pk",
        "user_id": "user_entity_pk"
      }
    ],
    "blog": [
      {
        "id": "09944e04-f925-42e0-96e5-18e37ba419c5",
        "title": "The Future of Artificial Intelligence",
        "content": "Lorem ipsum dolor sit amet, consectetur adipiscing elit.",
        "status": "Draft",
        "created_at": "2023-09-04T13:50:25.437Z",
        "updated_at": "2023-09-05T05:29:05.159Z",
        "company_id": "main_entity_pk",
        "user_id": "user_entity_pk"
      },
      {
        "id": "98c288ef-276d-4b47-bb03-b4be150715f7",
        "title": "10 Tips for Effective Time Management",
        "content": "Sed ut perspiciatis unde omnis iste natus error sit voluptatem accusantium doloremque laudantium.",
        "status": "Published",
        "created_at": "2023-09-04T23:12:20.403Z",
        "updated_at": "2023-09-04T21:23:28.218Z",
        "company_id": "main_entity_pk",
        "user_id": "user_entity_pk"
      },
      {
        "id": "4e8235b2-058f-4a28-bcdd-dc4aa590345e",
        "title": "The Impact of Social Media on Society",
        "content": "Nemo enim ipsam voluptatem quia voluptas sit aspernatur aut odit aut fugit.",
        "status": "Archived",
        "created_at": "2023-09-04T20:44:52.481Z",
        "updated_at": "2023-09-04T15:19:05.441Z",
        "company_id": "main_entity_pk",
        "user_id": "user_entity_pk"
      },
      {
        "id": "4e708c0d-6021-41a5-8ad9-6ae7b3b5a83a",
        "title": "How to Improve Your Communication Skills",
        "content": "Ut enim ad minima veniam, quis nostrum exercitationem ullam corporis suscipit laboriosam.",
        "status": "Pending",
        "created_at": "2023-09-04T09:25:56.263Z",
        "updated_at": "2023-09-04T10:47:56.243Z",
        "company_id": "main_entity_pk",
        "user_id": "user_entity_pk"
      },
      {
        "id": "1c1f03f5-7b04-4eca-9a62-3b92c07d02b7",
        "title": "The Benefits of Regular Exercise",
        "content": "Duis aute irure dolor in reprehenderit in voluptate velit esse cillum dolore eu fugiat nulla pariatur.",
        "status": "Reviewed",
        "created_at": "2023-09-04T11:22:45.955Z",
        "updated_at": "2023-09-04T17:10:01.414Z",
        "company_id": "main_entity_pk",
        "user_id": "user_entity_pk"
      }
    ],
    "roqUser": [
      {
        "reference": "f628ebc5-714f-4492-ab32-56574fbcfaca",
        "email": "Richie_Harvey@yahoo.com",
        "firstName": "Mekhi",
        "lastName": "Beier",
        "active": true,
        "avatarUrl": "https://avatars.githubusercontent.com/u/66957154",
        "tenantId": null
      },
      {
        "reference": "98424267-c598-49ba-bee7-3f22ef3204cf",
        "email": "Dolores_McKenzie61@yahoo.com",
        "firstName": "Joey",
        "lastName": "Schmidt",
        "active": true,
        "avatarUrl": "https://cloudflare-ipfs.com/ipfs/Qmd3W5DuhgHirLHGVixi6V76LhCkZUz6pnFt5AJBiyvHye/avatar/311.jpg",
        "tenantId": null
      },
      {
        "reference": "f59123c7-80f0-4987-8deb-f456ccfb3e51",
        "email": "Isom.Jerde75@yahoo.com",
        "firstName": "Shemar",
        "lastName": "Berge",
        "active": true,
        "avatarUrl": "https://cloudflare-ipfs.com/ipfs/Qmd3W5DuhgHirLHGVixi6V76LhCkZUz6pnFt5AJBiyvHye/avatar/745.jpg",
        "tenantId": null
      },
      {
        "reference": "51e75fab-0ccc-46cb-8b0c-dcc5b2a9fc6d",
        "email": "Crystal.Toy0@gmail.com",
        "firstName": "Fanny",
        "lastName": "Rohan",
        "active": true,
        "avatarUrl": "https://cloudflare-ipfs.com/ipfs/Qmd3W5DuhgHirLHGVixi6V76LhCkZUz6pnFt5AJBiyvHye/avatar/291.jpg",
        "tenantId": null
      },
      {
        "reference": "bdf44c5f-2ed7-4ad4-ae66-75c0d3da5aa6",
        "email": "Providenci_Wyman-Watsica@gmail.com",
        "firstName": "Louvenia",
        "lastName": "King",
        "active": true,
        "avatarUrl": "https://avatars.githubusercontent.com/u/30491188",
        "tenantId": null
      }
    ]
  },
  {
    "invitation": [
      {
        "id": "ab6480e9-1a3d-4c83-97bc-33f35c7b78f9",
        "status": "Accepted",
        "expiry_date": "2023-09-04T22:40:53.315Z",
        "created_at": "2023-09-04T17:34:46.843Z",
        "updated_at": "2023-09-04T21:58:51.741Z",
        "company_id": "main_entity_pk",
        "user_id": "user_entity_pk"
      },
      {
        "id": "c531aa4c-5bfb-4797-95f3-ba1cf6e47dfa",
        "status": "Pending",
        "expiry_date": "2023-09-05T03:19:09.411Z",
        "created_at": "2023-09-04T13:05:31.210Z",
        "updated_at": "2023-09-04T18:54:46.456Z",
        "company_id": "main_entity_pk",
        "user_id": "user_entity_pk"
      },
      {
        "id": "6207c4fc-c465-4048-be3a-e4264a980972",
        "status": "Declined",
        "expiry_date": "2023-09-04T13:54:28.235Z",
        "created_at": "2023-09-04T18:29:46.620Z",
        "updated_at": "2023-09-04T17:38:40.919Z",
        "company_id": "main_entity_pk",
        "user_id": "user_entity_pk"
      },
      {
        "id": "097fa4f5-be99-4a84-b6b2-c1b035b7314a",
        "status": "Expired",
        "expiry_date": "2023-09-04T10:41:52.188Z",
        "created_at": "2023-09-05T00:44:28.504Z",
        "updated_at": "2023-09-04T19:07:24.942Z",
        "company_id": "main_entity_pk",
        "user_id": "user_entity_pk"
      },
      {
        "id": "f6c4a2ec-c532-40b3-9ddb-5ad2c65e4ef6",
        "status": "Cancelled",
        "expiry_date": "2023-09-04T15:14:06.544Z",
        "created_at": "2023-09-05T01:14:58.042Z",
        "updated_at": "2023-09-05T03:53:52.176Z",
        "company_id": "main_entity_pk",
        "user_id": "user_entity_pk"
      }
    ],
    "blog": [
      {
        "id": "3bb82ab7-8110-4aa3-906d-c9054e94503d",
        "title": "The Importance of Time Management",
        "content": "Lorem ipsum dolor sit amet, consectetur adipiscing elit.",
        "status": "Draft",
        "created_at": "2023-09-04T11:13:37.897Z",
        "updated_at": "2023-09-04T17:18:03.365Z",
        "company_id": "main_entity_pk",
        "user_id": "user_entity_pk"
      },
      {
        "id": "18e3a4cb-1eec-49cf-a836-d15b2c3c7613",
        "title": "Effective Strategies for Productivity",
        "content": "Sed ut perspiciatis unde omnis iste natus error sit voluptatem accusantium doloremque laudantium.",
        "status": "Published",
        "created_at": "2023-09-05T00:30:36.884Z",
        "updated_at": "2023-09-04T13:58:58.871Z",
        "company_id": "main_entity_pk",
        "user_id": "user_entity_pk"
      },
      {
        "id": "409d6582-69a8-442b-a2a2-f5b21ce1179f",
        "title": "Tips for Successful Remote Work",
        "content": "Nemo enim ipsam voluptatem quia voluptas sit aspernatur aut odit aut fugit.",
        "status": "Archived",
        "created_at": "2023-09-04T07:29:26.716Z",
        "updated_at": "2023-09-04T07:47:29.818Z",
        "company_id": "main_entity_pk",
        "user_id": "user_entity_pk"
      },
      {
        "id": "d6435967-33b4-4b14-bf19-1380a170ff49",
        "title": "How to Improve Communication Skills",
        "content": "Quis autem vel eum iure reprehenderit qui in ea voluptate velit esse quam nihil molestiae consequatur.",
        "status": "Pending Review",
        "created_at": "2023-09-05T03:49:21.801Z",
        "updated_at": "2023-09-04T15:29:58.498Z",
        "company_id": "main_entity_pk",
        "user_id": "user_entity_pk"
      },
      {
        "id": "ffec8860-5934-48b1-a781-0f4c868c4833",
        "title": "The Benefits of Regular Exercise",
        "content": "At vero eos et accusamus et iusto odio dignissimos ducimus qui blanditiis praesentium voluptatum deleniti atque corrupti quos dolores et quas molestias excepturi sint occaecati cupiditate non provident.",
        "status": "Deleted",
        "created_at": "2023-09-05T04:43:11.986Z",
        "updated_at": "2023-09-04T18:21:22.090Z",
        "company_id": "main_entity_pk",
        "user_id": "user_entity_pk"
      }
    ],
    "roqUser": [
      {
        "reference": "ddf82b19-1c1c-4b29-b7eb-d07cd05624a2",
        "email": "Camille.Kulas@hotmail.com",
        "firstName": "Curt",
        "lastName": "Moore",
        "active": true,
        "avatarUrl": "https://cloudflare-ipfs.com/ipfs/Qmd3W5DuhgHirLHGVixi6V76LhCkZUz6pnFt5AJBiyvHye/avatar/585.jpg",
        "tenantId": null
      },
      {
        "reference": "7561b3c9-2e1c-4a2e-93fa-2daf0511682e",
        "email": "Florian45@gmail.com",
        "firstName": "Johnathon",
        "lastName": "Little",
        "active": true,
        "avatarUrl": "https://avatars.githubusercontent.com/u/6798861",
        "tenantId": null
      },
      {
        "reference": "01b8e1a2-5bb1-4da4-b791-eb71ccb2a83c",
        "email": "Anahi37@gmail.com",
        "firstName": "Stephania",
        "lastName": "Hand",
        "active": true,
        "avatarUrl": "https://avatars.githubusercontent.com/u/40744331",
        "tenantId": null
      },
      {
        "reference": "8cc5616a-7302-4bb3-9983-df559dae1bfd",
        "email": "Jermain69@hotmail.com",
        "firstName": "Clifford",
        "lastName": "Reichel",
        "active": true,
        "avatarUrl": "https://cloudflare-ipfs.com/ipfs/Qmd3W5DuhgHirLHGVixi6V76LhCkZUz6pnFt5AJBiyvHye/avatar/283.jpg",
        "tenantId": null
      },
      {
        "reference": "83dd65e2-5910-4dd5-9d19-e607c0366e50",
        "email": "Nedra.Harber@gmail.com",
        "firstName": "Marshall",
        "lastName": "Goyette",
        "active": true,
        "avatarUrl": "https://avatars.githubusercontent.com/u/30019132",
        "tenantId": null
      }
    ]
  },
  {
    "invitation": [
      {
        "id": "7d161033-bc20-4c4d-a779-e58906442c60",
        "status": "Sent",
        "expiry_date": "2023-09-04T12:35:28.092Z",
        "created_at": "2023-09-04T18:56:16.937Z",
        "updated_at": "2023-09-05T01:44:22.142Z",
        "company_id": "main_entity_pk",
        "user_id": "user_entity_pk"
      },
      {
        "id": "ae8d3d5c-3d01-4cf7-a9a4-c85503c8ff89",
        "status": "Accepted",
        "expiry_date": "2023-09-05T02:50:13.831Z",
        "created_at": "2023-09-05T03:14:16.399Z",
        "updated_at": "2023-09-04T23:46:49.158Z",
        "company_id": "main_entity_pk",
        "user_id": "user_entity_pk"
      },
      {
        "id": "c0d6a97c-8d0b-41ae-b5ea-d25b4c2bf40d",
        "status": "Declined",
        "expiry_date": "2023-09-04T22:06:54.241Z",
        "created_at": "2023-09-05T02:39:07.605Z",
        "updated_at": "2023-09-05T03:45:43.176Z",
        "company_id": "main_entity_pk",
        "user_id": "user_entity_pk"
      },
      {
        "id": "8a6ea74a-214c-4eb0-a8f1-dbe9d4fb5e96",
        "status": "Pending",
        "expiry_date": "2023-09-04T14:44:39.375Z",
        "created_at": "2023-09-05T05:00:39.075Z",
        "updated_at": "2023-09-04T09:47:25.002Z",
        "company_id": "main_entity_pk",
        "user_id": "user_entity_pk"
      },
      {
        "id": "e3a4bcce-3a2e-4b7d-b316-50118c1d6d88",
        "status": "Expired",
        "expiry_date": "2023-09-04T08:41:03.184Z",
        "created_at": "2023-09-04T09:03:07.029Z",
        "updated_at": "2023-09-05T03:18:38.039Z",
        "company_id": "main_entity_pk",
        "user_id": "user_entity_pk"
      }
    ],
    "blog": [
      {
        "id": "e27db6d9-a5b4-4c16-be3f-c5d947adf47d",
        "title": "The Art of Programming",
        "content": "Lorem ipsum dolor sit amet, consectetur adipiscing elit.",
        "status": "Published",
        "created_at": "2023-09-04T22:24:03.387Z",
        "updated_at": "2023-09-04T18:16:46.785Z",
        "company_id": "main_entity_pk",
        "user_id": "user_entity_pk"
      },
      {
        "id": "b6e6f595-4bb6-44f3-a564-457282ecaf9e",
        "title": "Exploring New Horizons",
        "content": "Sed ut perspiciatis unde omnis iste natus error sit voluptatem.",
        "status": "Draft",
        "created_at": "2023-09-04T18:03:38.286Z",
        "updated_at": "2023-09-05T01:50:45.116Z",
        "company_id": "main_entity_pk",
        "user_id": "user_entity_pk"
      },
      {
        "id": "e0954bbc-552a-4c33-8512-f8fbf3000367",
        "title": "Mastering the Craft",
        "content": "Nemo enim ipsam voluptatem quia voluptas sit aspernatur aut odit aut fugit.",
        "status": "Pending",
        "created_at": "2023-09-04T10:21:05.263Z",
        "updated_at": "2023-09-04T15:29:17.552Z",
        "company_id": "main_entity_pk",
        "user_id": "user_entity_pk"
      },
      {
        "id": "e3f85542-2f87-4968-801b-6baad70d8b12",
        "title": "Unleashing Creativity",
        "content": "Neque porro quisquam est, qui dolorem ipsum quia dolor sit amet.",
        "status": "Archived",
        "created_at": "2023-09-05T00:20:44.933Z",
        "updated_at": "2023-09-04T09:12:40.059Z",
        "company_id": "main_entity_pk",
        "user_id": "user_entity_pk"
      },
      {
        "id": "99338480-2b79-40d5-bedf-3b1f22bdd353",
        "title": "Innovations in Technology",
        "content": "Lorem ipsum dolor sit amet, consectetur adipiscing elit, sed do eiusmod tempor incididunt ut labore et dolore magna aliqua.",
        "status": "Featured",
        "created_at": "2023-09-05T02:21:16.409Z",
        "updated_at": "2023-09-04T14:40:55.167Z",
        "company_id": "main_entity_pk",
        "user_id": "user_entity_pk"
      }
    ],
    "roqUser": [
      {
        "reference": "69a691e6-2b65-4bec-8eec-03befcee982c",
        "email": "Mikel_Yost@hotmail.com",
        "firstName": "Sherwood",
        "lastName": "Marks",
        "active": true,
        "avatarUrl": "https://cloudflare-ipfs.com/ipfs/Qmd3W5DuhgHirLHGVixi6V76LhCkZUz6pnFt5AJBiyvHye/avatar/308.jpg",
        "tenantId": null
      },
      {
        "reference": "ba282855-2f87-45e2-a00b-f40ecff31307",
        "email": "Libby.Labadie@yahoo.com",
        "firstName": "Katlyn",
        "lastName": "Kuphal",
        "active": true,
        "avatarUrl": "https://cloudflare-ipfs.com/ipfs/Qmd3W5DuhgHirLHGVixi6V76LhCkZUz6pnFt5AJBiyvHye/avatar/1090.jpg",
        "tenantId": null
      },
      {
        "reference": "cb96fba3-1985-47f2-8e03-d50258cb6c32",
        "email": "Gudrun_Corkery41@yahoo.com",
        "firstName": "Jesse",
        "lastName": "Langworth",
        "active": true,
        "avatarUrl": "https://avatars.githubusercontent.com/u/39404649",
        "tenantId": null
      },
      {
        "reference": "1e6e2e2a-1443-443e-804c-838eb620091f",
        "email": "Reynold_Corwin@hotmail.com",
        "firstName": "Kian",
        "lastName": "Rowe-Cartwright",
        "active": true,
        "avatarUrl": "https://avatars.githubusercontent.com/u/21534766",
        "tenantId": null
      },
      {
        "reference": "51b777db-728e-4019-aa5f-6694f49e7509",
        "email": "Antwon_Carter59@yahoo.com",
        "firstName": "Fredy",
        "lastName": "Boyer",
        "active": true,
        "avatarUrl": "https://cloudflare-ipfs.com/ipfs/Qmd3W5DuhgHirLHGVixi6V76LhCkZUz6pnFt5AJBiyvHye/avatar/242.jpg",
        "tenantId": null
      }
    ]
  },
  {
    "invitation": [
      {
        "id": "3a93123f-86e3-4b0c-887f-84201ff1b126",
        "status": "Sent",
        "expiry_date": "2023-09-05T01:36:12.606Z",
        "created_at": "2023-09-04T15:34:30.377Z",
        "updated_at": "2023-09-04T23:22:26.128Z",
        "company_id": "main_entity_pk",
        "user_id": "user_entity_pk"
      },
      {
        "id": "054e122a-891f-4cde-97e9-0541215c90b4",
        "status": "Accepted",
        "expiry_date": "2023-09-04T23:22:19.229Z",
        "created_at": "2023-09-04T11:42:46.510Z",
        "updated_at": "2023-09-04T17:51:13.287Z",
        "company_id": "main_entity_pk",
        "user_id": "user_entity_pk"
      },
      {
        "id": "e712011d-656a-4a93-86f3-4fd59628f812",
        "status": "Declined",
        "expiry_date": "2023-09-04T11:51:53.646Z",
        "created_at": "2023-09-04T18:22:51.589Z",
        "updated_at": "2023-09-04T19:54:33.735Z",
        "company_id": "main_entity_pk",
        "user_id": "user_entity_pk"
      },
      {
        "id": "eb4734a3-3e47-432e-8d6d-a0fe83124061",
        "status": "Pending",
        "expiry_date": "2023-09-04T08:57:07.670Z",
        "created_at": "2023-09-04T09:10:55.832Z",
        "updated_at": "2023-09-04T07:18:41.059Z",
        "company_id": "main_entity_pk",
        "user_id": "user_entity_pk"
      },
      {
        "id": "f40d2056-5d25-4b7d-8486-cbc5d7881164",
        "status": "Expired",
        "expiry_date": "2023-09-05T00:14:18.120Z",
        "created_at": "2023-09-04T14:15:44.372Z",
        "updated_at": "2023-09-04T20:58:13.833Z",
        "company_id": "main_entity_pk",
        "user_id": "user_entity_pk"
      }
    ],
    "blog": [
      {
        "id": "b43cbc97-6fba-4a39-8b9f-1a69437b9909",
        "title": "The Importance of Time Management",
        "content": "Lorem ipsum dolor sit amet, consectetur adipiscing elit.",
        "status": "Draft",
        "created_at": "2023-09-04T16:38:35.626Z",
        "updated_at": "2023-09-05T00:52:54.363Z",
        "company_id": "main_entity_pk",
        "user_id": "user_entity_pk"
      },
      {
        "id": "d29d7799-3228-44f8-8d70-8e4e8a5f4afd",
        "title": "Exploring the Wonders of Nature",
        "content": "Sed ut perspiciatis unde omnis iste natus error sit voluptatem accusantium doloremque laudantium.",
        "status": "Published",
        "created_at": "2023-09-04T10:45:51.988Z",
        "updated_at": "2023-09-04T08:14:10.708Z",
        "company_id": "main_entity_pk",
        "user_id": "user_entity_pk"
      },
      {
        "id": "adc9cc07-02a1-47b8-a193-ce42879b6699",
        "title": "Tips for Effective Communication",
        "content": "Nemo enim ipsam voluptatem quia voluptas sit aspernatur aut odit aut fugit.",
        "status": "Archived",
        "created_at": "2023-09-05T03:20:37.130Z",
        "updated_at": "2023-09-04T12:37:01.698Z",
        "company_id": "main_entity_pk",
        "user_id": "user_entity_pk"
      },
      {
        "id": "a325ce24-0f3a-4b31-a451-d806164cac62",
        "title": "The Art of Problem Solving",
        "content": "Quis autem vel eum iure reprehenderit qui in ea voluptate velit esse quam nihil molestiae consequatur.",
        "status": "Pending",
        "created_at": "2023-09-04T09:19:01.585Z",
        "updated_at": "2023-09-04T20:09:44.529Z",
        "company_id": "main_entity_pk",
        "user_id": "user_entity_pk"
      },
      {
        "id": "a6dda9b3-3f2c-4d22-99a6-3c8cb8cd5e87",
        "title": "Understanding the Basics of Finance",
        "content": "At vero eos et accusamus et iusto odio dignissimos ducimus qui blanditiis praesentium voluptatum deleniti atque corrupti quos dolores et quas molestias excepturi sint occaecati cupiditate non provident.",
        "status": "Deleted",
        "created_at": "2023-09-05T05:50:43.120Z",
        "updated_at": "2023-09-05T03:12:57.943Z",
        "company_id": "main_entity_pk",
        "user_id": "user_entity_pk"
      }
    ],
    "roqUser": [
      {
        "reference": "c04cec25-eae6-4099-a540-3e1ee17aa350",
        "email": "Catharine_Toy@hotmail.com",
        "firstName": "Cesar",
        "lastName": "Rowe",
        "active": true,
        "avatarUrl": "https://avatars.githubusercontent.com/u/83786523",
        "tenantId": null
      },
      {
        "reference": "a844dd65-7deb-4bf2-9455-d350d767768c",
        "email": "Violet_Hane@gmail.com",
        "firstName": "Elinore",
        "lastName": "Kertzmann",
        "active": true,
        "avatarUrl": "https://avatars.githubusercontent.com/u/83364040",
        "tenantId": null
      },
      {
        "reference": "98b24b72-b5ef-481c-8706-702f5c5effd9",
        "email": "Telly38@yahoo.com",
        "firstName": "Athena",
        "lastName": "Ernser",
        "active": true,
        "avatarUrl": "https://avatars.githubusercontent.com/u/26500031",
        "tenantId": null
      },
      {
        "reference": "0fc67631-03de-45c0-b6cf-463336e41ec7",
        "email": "Kenna12@yahoo.com",
        "firstName": "Geoffrey",
        "lastName": "Herzog",
        "active": true,
        "avatarUrl": "https://cloudflare-ipfs.com/ipfs/Qmd3W5DuhgHirLHGVixi6V76LhCkZUz6pnFt5AJBiyvHye/avatar/140.jpg",
        "tenantId": null
      },
      {
        "reference": "3ada31a6-d9aa-4eef-b7e4-c8d754ee7193",
        "email": "Mortimer_Daugherty@gmail.com",
        "firstName": "Caleigh",
        "lastName": "Botsford",
        "active": true,
        "avatarUrl": "https://cloudflare-ipfs.com/ipfs/Qmd3W5DuhgHirLHGVixi6V76LhCkZUz6pnFt5AJBiyvHye/avatar/395.jpg",
        "tenantId": null
      }
    ]
  },
  {
    "invitation": [
      {
        "id": "30a69373-00d6-4a08-8dbc-b7a35c183105",
        "status": "Sent",
        "expiry_date": "2023-09-04T07:41:18.406Z",
        "created_at": "2023-09-05T06:40:47.268Z",
        "updated_at": "2023-09-04T07:43:37.297Z",
        "company_id": "main_entity_pk",
        "user_id": "user_entity_pk"
      },
      {
        "id": "ec99df50-e121-43bb-bb79-8071b745464e",
        "status": "Accepted",
        "expiry_date": "2023-09-05T01:25:56.629Z",
        "created_at": "2023-09-04T23:06:34.725Z",
        "updated_at": "2023-09-05T06:45:39.858Z",
        "company_id": "main_entity_pk",
        "user_id": "user_entity_pk"
      },
      {
        "id": "e5a5b708-f693-4c1e-87d8-2230d6b9cd53",
        "status": "Declined",
        "expiry_date": "2023-09-04T12:37:56.452Z",
        "created_at": "2023-09-04T14:34:18.027Z",
        "updated_at": "2023-09-04T09:16:36.965Z",
        "company_id": "main_entity_pk",
        "user_id": "user_entity_pk"
      },
      {
        "id": "f55ec55a-a357-49fe-bee5-3b7adc05f8c5",
        "status": "Pending",
        "expiry_date": "2023-09-04T22:26:20.860Z",
        "created_at": "2023-09-05T03:40:40.876Z",
        "updated_at": "2023-09-04T10:37:01.438Z",
        "company_id": "main_entity_pk",
        "user_id": "user_entity_pk"
      },
      {
        "id": "aea3243f-55b3-40d0-ab3c-692d27a8c363",
        "status": "Expired",
        "expiry_date": "2023-09-04T15:33:55.398Z",
        "created_at": "2023-09-05T04:02:43.185Z",
        "updated_at": "2023-09-05T06:14:20.712Z",
        "company_id": "main_entity_pk",
        "user_id": "user_entity_pk"
      }
    ],
    "blog": [
      {
        "id": "48af74a4-6763-4fc6-a96c-623f9d95ac69",
        "title": "The Future of Artificial Intelligence",
        "content": "Lorem ipsum dolor sit amet, consectetur adipiscing elit.",
        "status": "Draft",
        "created_at": "2023-09-05T04:21:14.696Z",
        "updated_at": "2023-09-04T17:03:04.048Z",
        "company_id": "main_entity_pk",
        "user_id": "user_entity_pk"
      },
      {
        "id": "4f612775-b610-4089-927c-d42e6997c394",
        "title": "Exploring Blockchain Technology",
        "content": "Sed ut perspiciatis unde omnis iste natus error sit voluptatem accusantium doloremque laudantium.",
        "status": "Published",
        "created_at": "2023-09-04T22:59:02.064Z",
        "updated_at": "2023-09-04T08:41:58.595Z",
        "company_id": "main_entity_pk",
        "user_id": "user_entity_pk"
      },
      {
        "id": "995d1166-4604-4e2f-b85b-acdebb927663",
        "title": "Tips for Effective Time Management",
        "content": "At vero eos et accusamus et iusto odio dignissimos ducimus qui blanditiis praesentium voluptatum deleniti atque corrupti quos dolores et quas molestias excepturi sint occaecati cupiditate non provident.",
        "status": "Archived",
        "created_at": "2023-09-04T15:22:23.542Z",
        "updated_at": "2023-09-04T17:48:50.768Z",
        "company_id": "main_entity_pk",
        "user_id": "user_entity_pk"
      },
      {
        "id": "25487f21-81da-49b5-b27b-ff9cea641d0b",
        "title": "The Power of Positive Thinking",
        "content": "Nemo enim ipsam voluptatem quia voluptas sit aspernatur aut odit aut fugit, sed quia consequuntur magni dolores eos qui ratione voluptatem sequi nesciunt.",
        "status": "Pending Review",
        "created_at": "2023-09-04T16:45:41.970Z",
        "updated_at": "2023-09-04T08:20:10.675Z",
        "company_id": "main_entity_pk",
        "user_id": "user_entity_pk"
      },
      {
        "id": "9d39f1f2-d8f5-4914-83f4-5edc06a45562",
        "title": "Mastering the Art of Public Speaking",
        "content": "Neque porro quisquam est, qui dolorem ipsum quia dolor sit amet, consectetur, adipisci velit, sed quia non numquam eius modi tempora incidunt ut labore et dolore magnam aliquam quaerat voluptatem.",
        "status": "Featured",
        "created_at": "2023-09-04T22:11:09.591Z",
        "updated_at": "2023-09-04T23:37:11.395Z",
        "company_id": "main_entity_pk",
        "user_id": "user_entity_pk"
      }
    ],
    "roqUser": [
      {
        "reference": "2e695dcb-b49c-43f4-bb79-e96f7f909848",
        "email": "Monty_Leffler@gmail.com",
        "firstName": "Ken",
        "lastName": "Hickle",
        "active": true,
        "avatarUrl": "https://cloudflare-ipfs.com/ipfs/Qmd3W5DuhgHirLHGVixi6V76LhCkZUz6pnFt5AJBiyvHye/avatar/348.jpg",
        "tenantId": null
      },
      {
        "reference": "6eabbd57-fa13-422a-b064-fbf49dfb67b7",
        "email": "Kale25@yahoo.com",
        "firstName": "Estel",
        "lastName": "Kertzmann",
        "active": true,
        "avatarUrl": "https://cloudflare-ipfs.com/ipfs/Qmd3W5DuhgHirLHGVixi6V76LhCkZUz6pnFt5AJBiyvHye/avatar/1209.jpg",
        "tenantId": null
      },
      {
        "reference": "a881ef86-134a-4591-b2ce-7e6a5deb0b6f",
        "email": "Kory_Rice-Schimmel13@hotmail.com",
        "firstName": "Junius",
        "lastName": "Sporer-Kilback",
        "active": true,
        "avatarUrl": "https://cloudflare-ipfs.com/ipfs/Qmd3W5DuhgHirLHGVixi6V76LhCkZUz6pnFt5AJBiyvHye/avatar/1242.jpg",
        "tenantId": null
      },
      {
        "reference": "a8030ef2-ae67-4249-8ff6-931c2b479bc6",
        "email": "Isabell_Schimmel@hotmail.com",
        "firstName": "Jacques",
        "lastName": "Adams",
        "active": true,
        "avatarUrl": "https://cloudflare-ipfs.com/ipfs/Qmd3W5DuhgHirLHGVixi6V76LhCkZUz6pnFt5AJBiyvHye/avatar/206.jpg",
        "tenantId": null
      },
      {
        "reference": "87a2c6bb-64da-4793-97fd-927f6a1f2519",
        "email": "Maynard.Purdy75@yahoo.com",
        "firstName": "Myrl",
        "lastName": "Farrell",
        "active": true,
        "avatarUrl": "https://cloudflare-ipfs.com/ipfs/Qmd3W5DuhgHirLHGVixi6V76LhCkZUz6pnFt5AJBiyvHye/avatar/476.jpg",
        "tenantId": null
      }
    ]
  },
  {
    "invitation": [
      {
        "id": "f7b5c7a8-a26c-462e-87ac-6dde5abf30dd",
        "status": "Sent",
        "expiry_date": "2023-09-04T11:23:43.233Z",
        "created_at": "2023-09-05T03:15:14.555Z",
        "updated_at": "2023-09-04T10:05:03.038Z",
        "company_id": "main_entity_pk",
        "user_id": "user_entity_pk"
      },
      {
        "id": "1e3bceaa-2bdf-4065-af06-91e3f4c5ea45",
        "status": "Accepted",
        "expiry_date": "2023-09-04T13:35:57.212Z",
        "created_at": "2023-09-05T03:10:04.363Z",
        "updated_at": "2023-09-04T20:39:11.824Z",
        "company_id": "main_entity_pk",
        "user_id": "user_entity_pk"
      },
      {
        "id": "6e1905ef-72fc-4c19-90ed-1371b3caff41",
        "status": "Declined",
        "expiry_date": "2023-09-04T20:53:55.112Z",
        "created_at": "2023-09-04T13:45:01.270Z",
        "updated_at": "2023-09-04T11:27:23.083Z",
        "company_id": "main_entity_pk",
        "user_id": "user_entity_pk"
      },
      {
        "id": "70e706e0-f165-46f2-b530-83c69f201a65",
        "status": "Pending",
        "expiry_date": "2023-09-05T03:21:34.455Z",
        "created_at": "2023-09-04T20:12:36.474Z",
        "updated_at": "2023-09-04T22:18:39.989Z",
        "company_id": "main_entity_pk",
        "user_id": "user_entity_pk"
      },
      {
        "id": "29319ce6-f647-4c14-a0d8-10a26b3de05a",
        "status": "Expired",
        "expiry_date": "2023-09-04T09:21:36.954Z",
        "created_at": "2023-09-05T06:50:16.209Z",
        "updated_at": "2023-09-04T13:55:39.268Z",
        "company_id": "main_entity_pk",
        "user_id": "user_entity_pk"
      }
    ],
    "blog": [
      {
        "id": "09c325da-fd90-49e0-b795-f49c92021149",
        "title": "The Importance of Effective Communication",
        "content": "Lorem ipsum dolor sit amet, consectetur adipiscing elit.",
        "status": "Draft",
        "created_at": "2023-09-04T17:46:53.907Z",
        "updated_at": "2023-09-04T22:39:55.046Z",
        "company_id": "main_entity_pk",
        "user_id": "user_entity_pk"
      },
      {
        "id": "afd9b4c2-db21-4734-98f6-d53776207889",
        "title": "Tips for Successful Project Management",
        "content": "Sed ut perspiciatis unde omnis iste natus error sit voluptatem accusantium doloremque laudantium.",
        "status": "Published",
        "created_at": "2023-09-04T09:33:53.358Z",
        "updated_at": "2023-09-04T19:11:14.157Z",
        "company_id": "main_entity_pk",
        "user_id": "user_entity_pk"
      },
      {
        "id": "ea84a504-e17e-4028-ab83-c591c3e8e649",
        "title": "The Future of Artificial Intelligence",
        "content": "At vero eos et accusamus et iusto odio dignissimos ducimus qui blanditiis praesentium voluptatum deleniti atque corrupti quos dolores et quas molestias excepturi sint occaecati cupiditate non provident.",
        "status": "Archived",
        "created_at": "2023-09-04T11:51:48.660Z",
        "updated_at": "2023-09-04T09:53:23.942Z",
        "company_id": "main_entity_pk",
        "user_id": "user_entity_pk"
      },
      {
        "id": "4be7237d-2878-45d7-b811-0d5148879909",
        "title": "How to Improve Work-Life Balance",
        "content": "Nemo enim ipsam voluptatem quia voluptas sit aspernatur aut odit aut fugit, sed quia consequuntur magni dolores eos qui ratione voluptatem sequi nesciunt.",
        "status": "Pending",
        "created_at": "2023-09-04T14:08:36.187Z",
        "updated_at": "2023-09-05T03:28:09.619Z",
        "company_id": "main_entity_pk",
        "user_id": "user_entity_pk"
      },
      {
        "id": "49a0f72c-9ca6-4d93-8e29-9a9fffbf0c05",
        "title": "The Power of Positive Thinking",
        "content": "Neque porro quisquam est, qui dolorem ipsum quia dolor sit amet, consectetur, adipisci velit.",
        "status": "Deleted",
        "created_at": "2023-09-04T11:13:55.232Z",
        "updated_at": "2023-09-04T15:10:03.896Z",
        "company_id": "main_entity_pk",
        "user_id": "user_entity_pk"
      }
    ],
    "roqUser": [
      {
        "reference": "69f5db55-e819-4775-b98c-a39784981bc6",
        "email": "Joesph35@yahoo.com",
        "firstName": "Ellis",
        "lastName": "Kutch",
        "active": true,
        "avatarUrl": "https://avatars.githubusercontent.com/u/97613077",
        "tenantId": null
      },
      {
        "reference": "f919a829-2859-4f48-884e-b560944fac6a",
        "email": "Theodora86@yahoo.com",
        "firstName": "Beaulah",
        "lastName": "Treutel",
        "active": true,
        "avatarUrl": "https://cloudflare-ipfs.com/ipfs/Qmd3W5DuhgHirLHGVixi6V76LhCkZUz6pnFt5AJBiyvHye/avatar/115.jpg",
        "tenantId": null
      },
      {
        "reference": "2d2daffc-1476-410e-a826-d02bd0f53f71",
        "email": "Delfina.Braun74@yahoo.com",
        "firstName": "Waldo",
        "lastName": "Boyle",
        "active": true,
        "avatarUrl": "https://avatars.githubusercontent.com/u/72674509",
        "tenantId": null
      },
      {
        "reference": "6c6df0bf-9532-4a99-8b4a-c3f3bd7a9733",
        "email": "Shanelle.Ferry@gmail.com",
        "firstName": "Jeanette",
        "lastName": "Grimes",
        "active": true,
        "avatarUrl": "https://cloudflare-ipfs.com/ipfs/Qmd3W5DuhgHirLHGVixi6V76LhCkZUz6pnFt5AJBiyvHye/avatar/196.jpg",
        "tenantId": null
      },
      {
        "reference": "e5061e0a-1c43-48f2-ba6a-8e6638cdb2b5",
        "email": "Jaycee_Flatley@yahoo.com",
        "firstName": "Emmanuelle",
        "lastName": "Doyle",
        "active": true,
        "avatarUrl": "https://avatars.githubusercontent.com/u/46500373",
        "tenantId": null
      }
    ]
  },
  {
    "invitation": [
      {
        "id": "ff64e615-a4e9-43a4-9106-03067e99455a",
        "status": "Sent",
        "expiry_date": "2023-09-04T07:15:52.388Z",
        "created_at": "2023-09-04T14:45:22.300Z",
        "updated_at": "2023-09-04T07:04:08.714Z",
        "company_id": "main_entity_pk",
        "user_id": "user_entity_pk"
      },
      {
        "id": "a3d38f29-7dd9-4262-885b-e93775f38bcd",
        "status": "Accepted",
        "expiry_date": "2023-09-04T19:51:39.560Z",
        "created_at": "2023-09-04T12:14:37.291Z",
        "updated_at": "2023-09-04T10:27:13.787Z",
        "company_id": "main_entity_pk",
        "user_id": "user_entity_pk"
      },
      {
        "id": "eac04ca4-3228-4ba3-9f5e-b6a6cf123030",
        "status": "Declined",
        "expiry_date": "2023-09-04T09:38:32.038Z",
        "created_at": "2023-09-04T14:09:50.625Z",
        "updated_at": "2023-09-04T21:46:26.660Z",
        "company_id": "main_entity_pk",
        "user_id": "user_entity_pk"
      },
      {
        "id": "01f6f28f-6379-4e18-901f-3ed4c34f0507",
        "status": "Pending",
        "expiry_date": "2023-09-04T09:07:24.459Z",
        "created_at": "2023-09-04T09:10:52.991Z",
        "updated_at": "2023-09-04T12:55:00.212Z",
        "company_id": "main_entity_pk",
        "user_id": "user_entity_pk"
      },
      {
        "id": "c5178fee-0fc5-44e1-b3d4-a53293ae0e2d",
        "status": "Expired",
        "expiry_date": "2023-09-04T23:03:02.832Z",
        "created_at": "2023-09-04T20:21:34.918Z",
        "updated_at": "2023-09-04T22:23:02.659Z",
        "company_id": "main_entity_pk",
        "user_id": "user_entity_pk"
      }
    ],
    "blog": [
      {
        "id": "79374a58-5aaf-4594-abc8-4661c74654b1",
        "title": "The Art of Productivity",
        "content": "Lorem ipsum dolor sit amet, consectetur adipiscing elit.",
        "status": "Draft",
        "created_at": "2023-09-04T08:12:11.870Z",
        "updated_at": "2023-09-04T16:07:13.901Z",
        "company_id": "main_entity_pk",
        "user_id": "user_entity_pk"
      },
      {
        "id": "66dfa844-c8dc-425b-8221-f9133c600c40",
        "title": "Exploring New Horizons",
        "content": "Sed ut perspiciatis unde omnis iste natus error sit voluptatem accusantium doloremque laudantium.",
        "status": "Published",
        "created_at": "2023-09-04T10:03:14.758Z",
        "updated_at": "2023-09-05T03:36:40.504Z",
        "company_id": "main_entity_pk",
        "user_id": "user_entity_pk"
      },
      {
        "id": "7afe06a8-e6de-47fb-8c2b-a3ae7662d52d",
        "title": "Unlocking Creativity",
        "content": "Nemo enim ipsam voluptatem quia voluptas sit aspernatur aut odit aut fugit.",
        "status": "Archived",
        "created_at": "2023-09-04T09:33:31.369Z",
        "updated_at": "2023-09-05T06:21:51.053Z",
        "company_id": "main_entity_pk",
        "user_id": "user_entity_pk"
      },
      {
        "id": "f6ecb02e-6255-41ce-9f39-27508dee6d30",
        "title": "Mastering Time Management",
        "content": "Neque porro quisquam est, qui dolorem ipsum quia dolor sit amet, consectetur, adipisci velit.",
        "status": "Pending",
        "created_at": "2023-09-05T01:18:30.160Z",
        "updated_at": "2023-09-04T08:33:42.240Z",
        "company_id": "main_entity_pk",
        "user_id": "user_entity_pk"
      },
      {
        "id": "e5356da1-ddfa-4df1-b628-8d773a1d721b",
        "title": "Embracing Change",
        "content": "Lorem ipsum dolor sit amet, consectetur adipiscing elit, sed do eiusmod tempor incididunt ut labore et dolore magna aliqua.",
        "status": "Reviewed",
        "created_at": "2023-09-04T15:28:18.682Z",
        "updated_at": "2023-09-04T21:51:08.333Z",
        "company_id": "main_entity_pk",
        "user_id": "user_entity_pk"
      }
    ],
    "roqUser": [
      {
        "reference": "6a55bd56-93aa-4a0d-834e-6af3bfa60466",
        "email": "Jaylin_Considine29@gmail.com",
        "firstName": "Ally",
        "lastName": "Armstrong",
        "active": true,
        "avatarUrl": "https://cloudflare-ipfs.com/ipfs/Qmd3W5DuhgHirLHGVixi6V76LhCkZUz6pnFt5AJBiyvHye/avatar/899.jpg",
        "tenantId": null
      },
      {
        "reference": "fc026e04-7e78-4389-a469-388269f336bc",
        "email": "Laverne58@yahoo.com",
        "firstName": "Nikita",
        "lastName": "Grant",
        "active": true,
        "avatarUrl": "https://avatars.githubusercontent.com/u/73388469",
        "tenantId": null
      },
      {
        "reference": "961d6ce9-b32a-4353-a7a9-efe3ab5d67e8",
        "email": "Georgianna.Fay0@yahoo.com",
        "firstName": "Cary",
        "lastName": "Parker",
        "active": true,
        "avatarUrl": "https://avatars.githubusercontent.com/u/79189161",
        "tenantId": null
      },
      {
        "reference": "8d1127f4-b81b-4a43-9213-fbdb606742ec",
        "email": "Miles33@yahoo.com",
        "firstName": "Cassandre",
        "lastName": "Pfannerstill",
        "active": true,
        "avatarUrl": "https://cloudflare-ipfs.com/ipfs/Qmd3W5DuhgHirLHGVixi6V76LhCkZUz6pnFt5AJBiyvHye/avatar/1121.jpg",
        "tenantId": null
      },
      {
        "reference": "0fbb7dc6-db56-4d91-b9c2-686a24b7b70a",
        "email": "Felipe_Cassin51@gmail.com",
        "firstName": "Dameon",
        "lastName": "Wintheiser",
        "active": true,
        "avatarUrl": "https://avatars.githubusercontent.com/u/63398993",
        "tenantId": null
      }
    ]
  },
  {
    "invitation": [
      {
        "id": "cf45a360-f23e-4d3d-92ac-b31f2603cb53",
        "status": "Sent",
        "expiry_date": "2023-09-04T17:47:11.154Z",
        "created_at": "2023-09-04T20:06:42.639Z",
        "updated_at": "2023-09-05T01:16:38.306Z",
        "company_id": "main_entity_pk",
        "user_id": "user_entity_pk"
      },
      {
        "id": "7a254c26-b49a-40f8-a8cc-349545d892b0",
        "status": "Accepted",
        "expiry_date": "2023-09-04T07:15:50.571Z",
        "created_at": "2023-09-05T03:33:50.484Z",
        "updated_at": "2023-09-04T21:17:57.923Z",
        "company_id": "main_entity_pk",
        "user_id": "user_entity_pk"
      },
      {
        "id": "d013587a-496f-46e8-94dc-fd91b027c335",
        "status": "Declined",
        "expiry_date": "2023-09-04T19:44:21.595Z",
        "created_at": "2023-09-04T21:13:22.008Z",
        "updated_at": "2023-09-04T10:43:28.011Z",
        "company_id": "main_entity_pk",
        "user_id": "user_entity_pk"
      },
      {
        "id": "57c42009-cd51-4d83-b463-01bd82985cd1",
        "status": "Pending",
        "expiry_date": "2023-09-04T07:51:57.739Z",
        "created_at": "2023-09-04T13:35:20.006Z",
        "updated_at": "2023-09-05T01:01:55.244Z",
        "company_id": "main_entity_pk",
        "user_id": "user_entity_pk"
      },
      {
        "id": "e49522a2-dd92-4eaa-8cf9-48a2a1661922",
        "status": "Expired",
        "expiry_date": "2023-09-05T05:20:21.243Z",
        "created_at": "2023-09-05T02:49:30.131Z",
        "updated_at": "2023-09-05T02:11:32.380Z",
        "company_id": "main_entity_pk",
        "user_id": "user_entity_pk"
      }
    ],
    "blog": [
      {
        "id": "346a58a3-8926-46c1-9894-95a1048df28a",
        "title": "The Future of Technology",
        "content": "Lorem ipsum dolor sit amet, consectetur adipiscing elit.",
        "status": "Draft",
        "created_at": "2023-09-04T19:11:52.896Z",
        "updated_at": "2023-09-04T16:05:27.903Z",
        "company_id": "main_entity_pk",
        "user_id": "user_entity_pk"
      },
      {
        "id": "f55f17c0-f736-470e-808f-3ad918fc1339",
        "title": "Tips for Successful Entrepreneurship",
        "content": "Sed ut perspiciatis unde omnis iste natus error sit voluptatem accusantium doloremque laudantium.",
        "status": "Published",
        "created_at": "2023-09-04T22:38:11.872Z",
        "updated_at": "2023-09-04T23:44:28.298Z",
        "company_id": "main_entity_pk",
        "user_id": "user_entity_pk"
      },
      {
        "id": "1b270e16-4b10-4bf6-8eb6-2251b9a54f8a",
        "title": "The Importance of Work-Life Balance",
        "content": "Nemo enim ipsam voluptatem quia voluptas sit aspernatur aut odit aut fugit.",
        "status": "Archived",
        "created_at": "2023-09-05T03:26:42.700Z",
        "updated_at": "2023-09-04T21:05:28.964Z",
        "company_id": "main_entity_pk",
        "user_id": "user_entity_pk"
      },
      {
        "id": "99ec7ca5-7675-4ef1-82f3-9e0a2deafdd4",
        "title": "Exploring New Frontiers in Science",
        "content": "Quis autem vel eum iure reprehenderit qui in ea voluptate velit esse quam nihil molestiae consequatur.",
        "status": "Pending Review",
        "created_at": "2023-09-04T21:57:46.407Z",
        "updated_at": "2023-09-04T09:23:48.194Z",
        "company_id": "main_entity_pk",
        "user_id": "user_entity_pk"
      },
      {
        "id": "61d99c2e-5266-48aa-adb7-d717ad6f3b44",
        "title": "The Art of Effective Communication",
        "content": "At vero eos et accusamus et iusto odio dignissimos ducimus qui blanditiis praesentium voluptatum deleniti atque corrupti quos dolores et quas molestias excepturi sint occaecati cupiditate non provident.",
        "status": "Featured",
        "created_at": "2023-09-04T09:21:09.310Z",
        "updated_at": "2023-09-04T19:08:33.178Z",
        "company_id": "main_entity_pk",
        "user_id": "user_entity_pk"
      }
    ],
    "roqUser": [
      {
        "reference": "07e6abd4-5024-4fef-963d-a4eb6be6dbef",
        "email": "Annetta_Bahringer23@gmail.com",
        "firstName": "Brandyn",
        "lastName": "Rippin",
        "active": true,
        "avatarUrl": "https://avatars.githubusercontent.com/u/16279745",
        "tenantId": null
      },
      {
        "reference": "37eb2fb8-833b-4119-839e-fb86362f89a8",
        "email": "Sydney_Bartell@yahoo.com",
        "firstName": "Maida",
        "lastName": "Renner",
        "active": true,
        "avatarUrl": "https://avatars.githubusercontent.com/u/5484370",
        "tenantId": null
      },
      {
        "reference": "e3856746-918b-4993-bd0c-1cd90820f241",
        "email": "Erwin83@hotmail.com",
        "firstName": "Collin",
        "lastName": "Swaniawski",
        "active": true,
        "avatarUrl": "https://cloudflare-ipfs.com/ipfs/Qmd3W5DuhgHirLHGVixi6V76LhCkZUz6pnFt5AJBiyvHye/avatar/1005.jpg",
        "tenantId": null
      },
      {
        "reference": "8efa741b-9eda-4a20-8c9a-641832b8c03d",
        "email": "Conner.Jacobi2@hotmail.com",
        "firstName": "Skye",
        "lastName": "Ryan",
        "active": true,
        "avatarUrl": "https://cloudflare-ipfs.com/ipfs/Qmd3W5DuhgHirLHGVixi6V76LhCkZUz6pnFt5AJBiyvHye/avatar/58.jpg",
        "tenantId": null
      },
      {
        "reference": "c129b839-f3fd-4df9-bf9c-705859df8a01",
        "email": "Samir19@hotmail.com",
        "firstName": "Brady",
        "lastName": "Beer",
        "active": true,
        "avatarUrl": "https://cloudflare-ipfs.com/ipfs/Qmd3W5DuhgHirLHGVixi6V76LhCkZUz6pnFt5AJBiyvHye/avatar/1228.jpg",
        "tenantId": null
      }
    ]
  },
  {
    "invitation": [
      {
        "id": "a0bd1efd-2ed6-4444-a83e-794fd609c937",
        "status": "Sent",
        "expiry_date": "2023-09-04T20:35:26.483Z",
        "created_at": "2023-09-04T19:47:41.159Z",
        "updated_at": "2023-09-04T22:33:43.789Z",
        "company_id": "main_entity_pk",
        "user_id": "user_entity_pk"
      },
      {
        "id": "51dcd927-28a6-4280-b9b7-fa794dca66ad",
        "status": "Accepted",
        "expiry_date": "2023-09-04T23:17:06.275Z",
        "created_at": "2023-09-04T20:37:05.040Z",
        "updated_at": "2023-09-04T14:12:40.073Z",
        "company_id": "main_entity_pk",
        "user_id": "user_entity_pk"
      },
      {
        "id": "3ec87adb-99ad-4b75-b9a0-08679002eae6",
        "status": "Declined",
        "expiry_date": "2023-09-04T23:20:09.964Z",
        "created_at": "2023-09-05T06:03:58.545Z",
        "updated_at": "2023-09-04T07:24:22.138Z",
        "company_id": "main_entity_pk",
        "user_id": "user_entity_pk"
      },
      {
        "id": "098fd0a0-ebe0-4d89-b6d6-2dd4e45300b5",
        "status": "Pending",
        "expiry_date": "2023-09-05T00:51:22.684Z",
        "created_at": "2023-09-04T19:34:52.492Z",
        "updated_at": "2023-09-04T08:42:17.614Z",
        "company_id": "main_entity_pk",
        "user_id": "user_entity_pk"
      },
      {
        "id": "d26c1ae5-3d73-4de2-9981-f819b2e619af",
        "status": "Expired",
        "expiry_date": "2023-09-04T07:57:51.595Z",
        "created_at": "2023-09-05T05:39:57.052Z",
        "updated_at": "2023-09-05T03:02:59.542Z",
        "company_id": "main_entity_pk",
        "user_id": "user_entity_pk"
      }
    ],
    "blog": [
      {
        "id": "1ea6b447-7016-42fe-9cc7-2aff34c6a763",
        "title": "The Importance of Communication",
        "content": "Lorem ipsum dolor sit amet, consectetur adipiscing elit.",
        "status": "Published",
        "created_at": "2023-09-04T15:11:26.465Z",
        "updated_at": "2023-09-04T14:14:19.010Z",
        "company_id": "main_entity_pk",
        "user_id": "user_entity_pk"
      },
      {
        "id": "aae69af4-6c87-438c-86fa-756a6062acdf",
        "title": "10 Tips for Productivity",
        "content": "Sed ut perspiciatis unde omnis iste natus error sit voluptatem.",
        "status": "Draft",
        "created_at": "2023-09-04T23:04:34.233Z",
        "updated_at": "2023-09-04T22:26:31.894Z",
        "company_id": "main_entity_pk",
        "user_id": "user_entity_pk"
      },
      {
        "id": "71a146e9-e826-49ba-8bf5-6a84bfc90251",
        "title": "Exploring New Horizons",
        "content": "Nemo enim ipsam voluptatem quia voluptas sit aspernatur.",
        "status": "Pending",
        "created_at": "2023-09-04T17:11:30.500Z",
        "updated_at": "2023-09-05T02:24:04.059Z",
        "company_id": "main_entity_pk",
        "user_id": "user_entity_pk"
      },
      {
        "id": "fa649cd3-6439-4ff4-bccf-2f3818f338aa",
        "title": "The Art of Problem Solving",
        "content": "Neque porro quisquam est, qui dolorem ipsum quia dolor sit amet.",
        "status": "Archived",
        "created_at": "2023-09-05T03:41:43.530Z",
        "updated_at": "2023-09-04T10:28:43.784Z",
        "company_id": "main_entity_pk",
        "user_id": "user_entity_pk"
      },
      {
        "id": "9fb20230-fb5a-4088-90ae-b4536ee5517c",
        "title": "Unlocking Creativity",
        "content": "Lorem ipsum dolor sit amet, consectetur adipiscing elit, sed do eiusmod tempor incididunt ut labore et dolore magna aliqua.",
        "status": "Featured",
        "created_at": "2023-09-04T13:37:41.978Z",
        "updated_at": "2023-09-05T05:38:06.563Z",
        "company_id": "main_entity_pk",
        "user_id": "user_entity_pk"
      }
    ],
    "roqUser": [
      {
        "reference": "a703df02-c8bc-4569-a926-2f6303056d44",
        "email": "Daphney.Weimann@hotmail.com",
        "firstName": "Roderick",
        "lastName": "Feeney-Fay",
        "active": true,
        "avatarUrl": "https://cloudflare-ipfs.com/ipfs/Qmd3W5DuhgHirLHGVixi6V76LhCkZUz6pnFt5AJBiyvHye/avatar/704.jpg",
        "tenantId": null
      },
      {
        "reference": "c6bcb2b3-9f57-4930-a79e-fa8efab09b8d",
        "email": "Haven_Johnston@hotmail.com",
        "firstName": "Presley",
        "lastName": "Rogahn-Leannon",
        "active": true,
        "avatarUrl": "https://avatars.githubusercontent.com/u/32252375",
        "tenantId": null
      },
      {
        "reference": "dc5b9cf1-a615-45db-88bf-1c8e7a31920a",
        "email": "Camron88@hotmail.com",
        "firstName": "Ellen",
        "lastName": "Stokes",
        "active": true,
        "avatarUrl": "https://cloudflare-ipfs.com/ipfs/Qmd3W5DuhgHirLHGVixi6V76LhCkZUz6pnFt5AJBiyvHye/avatar/508.jpg",
        "tenantId": null
      },
      {
        "reference": "aa3548b1-c660-43cb-af48-9c6bc246718d",
        "email": "Brett81@hotmail.com",
        "firstName": "Lourdes",
        "lastName": "Langosh-Gusikowski",
        "active": true,
        "avatarUrl": "https://cloudflare-ipfs.com/ipfs/Qmd3W5DuhgHirLHGVixi6V76LhCkZUz6pnFt5AJBiyvHye/avatar/110.jpg",
        "tenantId": null
      },
      {
        "reference": "a19ec7ad-4c3c-4197-b09a-ee325af8e0d9",
        "email": "Felicia.Friesen@hotmail.com",
        "firstName": "Kathlyn",
        "lastName": "Pfeffer",
        "active": true,
        "avatarUrl": "https://avatars.githubusercontent.com/u/77726109",
        "tenantId": null
      }
    ]
  },
  {
    "invitation": [
      {
        "id": "41e85ee1-46d5-4b4b-8128-375e71b08695",
        "status": "Accepted",
        "expiry_date": "2023-09-04T16:57:41.443Z",
        "created_at": "2023-09-04T11:27:17.992Z",
        "updated_at": "2023-09-05T04:45:13.126Z",
        "company_id": "main_entity_pk",
        "user_id": "user_entity_pk"
      },
      {
        "id": "e88997ed-21d5-4a22-ad65-c1b890562582",
        "status": "Declined",
        "expiry_date": "2023-09-04T17:38:24.288Z",
        "created_at": "2023-09-04T12:25:07.862Z",
        "updated_at": "2023-09-04T15:04:32.852Z",
        "company_id": "main_entity_pk",
        "user_id": "user_entity_pk"
      },
      {
        "id": "2b3487dd-efe9-4dc8-979b-0261e408258c",
        "status": "Pending",
        "expiry_date": "2023-09-05T06:05:42.325Z",
        "created_at": "2023-09-04T20:03:06.192Z",
        "updated_at": "2023-09-04T14:54:16.287Z",
        "company_id": "main_entity_pk",
        "user_id": "user_entity_pk"
      },
      {
        "id": "994eaecb-7b0a-480f-8d0f-3dbb24903ff0",
        "status": "Expired",
        "expiry_date": "2023-09-04T09:45:44.561Z",
        "created_at": "2023-09-04T08:18:13.412Z",
        "updated_at": "2023-09-04T20:49:23.319Z",
        "company_id": "main_entity_pk",
        "user_id": "user_entity_pk"
      },
      {
        "id": "b8dc2f5d-3043-450b-8fe8-e1a21531e874",
        "status": "Cancelled",
        "expiry_date": "2023-09-04T18:03:25.460Z",
        "created_at": "2023-09-04T09:40:15.847Z",
        "updated_at": "2023-09-05T01:22:01.999Z",
        "company_id": "main_entity_pk",
        "user_id": "user_entity_pk"
      }
    ],
    "blog": [
      {
        "id": "dbaeb194-9711-4cc5-b181-8f17282efd8b",
        "title": "The Future of Artificial Intelligence",
        "content": "Lorem ipsum dolor sit amet, consectetur adipiscing elit.",
        "status": "Published",
        "created_at": "2023-09-04T11:27:25.732Z",
        "updated_at": "2023-09-04T07:52:15.810Z",
        "company_id": "main_entity_pk",
        "user_id": "user_entity_pk"
      },
      {
        "id": "6684b172-d1b6-496d-a0cd-b745b12598e3",
        "title": "Tips for Effective Time Management",
        "content": "Sed ut perspiciatis unde omnis iste natus error sit voluptatem.",
        "status": "Draft",
        "created_at": "2023-09-04T12:09:23.582Z",
        "updated_at": "2023-09-04T19:22:51.495Z",
        "company_id": "main_entity_pk",
        "user_id": "user_entity_pk"
      },
      {
        "id": "be69916f-d234-4ddf-876a-22af8d6715ca",
        "title": "How to Build a Successful Startup",
        "content": "At vero eos et accusamus et iusto odio dignissimos ducimus.",
        "status": "Pending",
        "created_at": "2023-09-04T18:27:15.628Z",
        "updated_at": "2023-09-04T13:14:02.109Z",
        "company_id": "main_entity_pk",
        "user_id": "user_entity_pk"
      },
      {
        "id": "dfc40a14-c225-450b-9238-50f900984101",
        "title": "The Impact of Social Media on Society",
        "content": "Nemo enim ipsam voluptatem quia voluptas sit aspernatur.",
        "status": "Archived",
        "created_at": "2023-09-04T20:25:11.351Z",
        "updated_at": "2023-09-04T15:28:39.290Z",
        "company_id": "main_entity_pk",
        "user_id": "user_entity_pk"
      },
      {
        "id": "0c100c7f-c272-441e-baf4-bcb04fe151a3",
        "title": "The Benefits of Regular Exercise",
        "content": "Neque porro quisquam est, qui dolorem ipsum quia dolor sit amet.",
        "status": "Deleted",
        "created_at": "2023-09-04T14:27:07.190Z",
        "updated_at": "2023-09-04T07:51:59.773Z",
        "company_id": "main_entity_pk",
        "user_id": "user_entity_pk"
      }
    ],
    "roqUser": [
      {
        "reference": "1c2ee369-a139-4951-a5d9-9726c198ec27",
        "email": "Velva85@hotmail.com",
        "firstName": "Destin",
        "lastName": "Greenfelder",
        "active": true,
        "avatarUrl": "https://cloudflare-ipfs.com/ipfs/Qmd3W5DuhgHirLHGVixi6V76LhCkZUz6pnFt5AJBiyvHye/avatar/433.jpg",
        "tenantId": null
      },
      {
        "reference": "528fd49c-f4e9-4a4d-9643-2b6ffc43e06b",
        "email": "Oceane.Hamill@gmail.com",
        "firstName": "Leanne",
        "lastName": "Ortiz",
        "active": true,
        "avatarUrl": "https://avatars.githubusercontent.com/u/3432747",
        "tenantId": null
      },
      {
        "reference": "7ce9a397-0369-447d-8af7-2b7acd1b5720",
        "email": "Felicity_OKon@hotmail.com",
        "firstName": "Angie",
        "lastName": "Tromp",
        "active": true,
        "avatarUrl": "https://cloudflare-ipfs.com/ipfs/Qmd3W5DuhgHirLHGVixi6V76LhCkZUz6pnFt5AJBiyvHye/avatar/972.jpg",
        "tenantId": null
      },
      {
        "reference": "3a717593-547e-4014-917f-0c094f67800e",
        "email": "Morris_Hirthe22@yahoo.com",
        "firstName": "Terrance",
        "lastName": "Mosciski",
        "active": true,
        "avatarUrl": "https://avatars.githubusercontent.com/u/4889851",
        "tenantId": null
      },
      {
        "reference": "8cce8229-6e34-46ea-86d2-e3723caa6f0a",
        "email": "Leatha73@hotmail.com",
        "firstName": "Alexandrine",
        "lastName": "Schuppe",
        "active": true,
        "avatarUrl": "https://cloudflare-ipfs.com/ipfs/Qmd3W5DuhgHirLHGVixi6V76LhCkZUz6pnFt5AJBiyvHye/avatar/467.jpg",
        "tenantId": null
      }
    ]
  }
]
